ZIZHUOffice365ManagementAPI/ZIZHUOffice365ManagementAPI.py
ZIZHUOffice365ManagementAPI/__init__.py
zizhuoffice365managementapi-0.0.2.dist-info/licenses/LICENSE
zizhuoffice365managementapi-0.0.2.dist-info/METADATA
zizhuoffice365managementapi-0.0.2.dist-info/WHEEL
zizhuoffice365managementapi-0.0.2.dist-info/top_level.txt
zizhuoffice365managementapi-0.0.2.dist-info/RECORD
