Metadata-Version: 2.4
Name: ZIZHUOffice365ManagementAPI
Version: 0.0.2
Summary: Python SDK for Office365ManageAPI
Author-email: Qi Dong <doqi@microsoft.com>, Dongli Pan <dongli.pan@microsoft.com>
License-Expression: MIT
Project-URL: Homepage, https://github.com/APACMW/APACMWOffice365ManagementAPIModule
Project-URL: Issues, https://github.com/APACMW/APACMWOffice365ManagementAPIModule
Classifier: Programming Language :: Python :: 3
Classifier: Operating System :: OS Independent
Requires-Python: >=3.9
License-File: LICENSE
Dynamic: license-file
